<?xml version='1.0' encoding='UTF-8'?>
<ITResourceOrchestration xmlns="http://modeliosoft/xsddesigner/a22bd60b-ee3d-425c-8618-beb6a854051a/ITResource.xsd" xmlns:xsi="http://www.w3.org/2001/XMLSchema-instance" id="omspl_test_4_20" xsi:schemaLocation="http://modeliosoft/xsddesigner/a22bd60b-ee3d-425c-8618-beb6a854051a/ITResource.xsd ../../xsd/mspl.xsd">
  <ITResource>
    <configuration xsi:type="AuthorizationIntents">
      <capability>
        <Name>KubernetesNetworkFiltering</Name>
      </capability>
      <forbiddenConnectionList>
        <configurationRuleAction xsi:type="KubernetesNetworkFilteringAction">
          <KubernetesNetworkFilteringActionType>DENY</KubernetesNetworkFilteringActionType>
        </configurationRuleAction>
        <configurationCondition xsi:type="KubernetesNetworkFilteringCondition">
          <isCNF>false</isCNF>
          <source xsi:type="CIDRSelector">
            <isHostCluster>true</isHostCluster>
            <addressRange>172.30.0.0/16</addressRange>
          </source>
          <sourcePort>1555</sourcePort>
          <destination xsi:type="PodNamespaceSelector">
            <isHostCluster>false</isHostCluster>
            <pod>
              <key>service</key>
              <value>metrics</value>
            </pod>
            <namespace>
              <key>env</key>
              <value>test</value>
            </namespace>
          </destination>
          <destinationPort>70-78</destinationPort>
          <protocolType>UDP</protocolType>
        </configurationCondition>
        <Name>AuthorizationForbidden_4_20</Name>
        <isCNF>false</isCNF>
      </forbiddenConnectionList>
    </configuration>
  </ITResource>
</ITResourceOrchestration>